list2group.py
list2group-0.0.1.dist-info/LICENSE.txt
list2group-0.0.1.dist-info/METADATA
list2group-0.0.1.dist-info/WHEEL
list2group-0.0.1.dist-info/top_level.txt
list2group-0.0.1.dist-info/RECORD
